{
  "main": {
    "id": "d5cc49bf1cd698fb",
    "type": "split",
    "children": [
      {
        "id": "369cb9650b6551bc",
        "type": "tabs",
        "children": [
          {
            "id": "ebaeefd887063772",
            "type": "leaf",
            "state": {
              "type": "graph",
              "state": {}
            }
          },
          {
            "id": "d43d58866a4c2563",
            "type": "leaf",
            "state": {
              "type": "markdown",
              "state": {
                "file": "Habits/chart.md",
                "mode": "source",
                "source": false
              }
            }
          },
          {
            "id": "8e514e59e1633575",
            "type": "leaf",
            "state": {
              "type": "markdown",
              "state": {
                "file": "journal/31-Jul.md",
                "mode": "source",
                "source": false
              }
            }
          },
          {
            "id": "dcf1d85d92a2e6d3",
            "type": "leaf",
            "state": {
              "type": "database-plugin",
              "state": {
                "file": "Habits/habit tracker.md"
              }
            }
          }
        ],
        "currentTab": 3
      }
    ],
    "direction": "vertical"
  },
  "left": {
    "id": "7b373f4c86ef1bb4",
    "type": "split",
    "children": [
      {
        "id": "056b3240d8353bc2",
        "type": "tabs",
        "dimension": 53.59168241965973,
        "children": [
          {
            "id": "e775b5396a74984d",
            "type": "leaf",
            "state": {
              "type": "file-explorer",
              "state": {
                "sortOrder": "byModifiedTime"
              }
            }
          },
          {
            "id": "6262a3c567452f3d",
            "type": "leaf",
            "state": {
              "type": "search",
              "state": {
                "query": "tag:#lesson",
                "matchingCase": false,
                "explainSearch": false,
                "collapseAll": false,
                "extraContext": false,
                "sortOrder": "alphabetical"
              }
            }
          },
          {
            "id": "20e562a0077c945d",
            "type": "leaf",
            "state": {
              "type": "bookmarks",
              "state": {}
            }
          },
          {
            "id": "b1256f54c1f7ba0d",
            "type": "leaf",
            "state": {
              "type": "mk-file-view",
              "state": {}
            }
          }
        ]
      },
      {
        "id": "15b3b7d9cffdec94",
        "type": "tabs",
        "dimension": 46.40831758034027,
        "children": [
          {
            "id": "a20fe457c72bc0e3",
            "type": "leaf",
            "state": {
              "type": "review-queue-list-view",
              "state": {}
            }
          },
          {
            "id": "55d7ad9d585e641c",
            "type": "leaf",
            "pinned": true,
            "state": {
              "type": "markdown",
              "state": {
                "file": "Home.md",
                "mode": "preview",
                "source": false
              },
              "pinned": true
            }
          }
        ],
        "currentTab": 1
      }
    ],
    "direction": "horizontal",
    "width": 427.5
  },
  "right": {
    "id": "640fa7646591537f",
    "type": "split",
    "children": [
      {
        "id": "16bccb08e7042bc6",
        "type": "tabs",
        "dimension": 32.30046948356807,
        "children": [
          {
            "id": "fe8bee43ece79a93",
            "type": "leaf",
            "state": {
              "type": "backlink",
              "state": {
                "file": "Habits/habit tracker.md",
                "collapseAll": true,
                "extraContext": false,
                "sortOrder": "alphabetical",
                "showSearch": false,
                "searchQuery": "",
                "backlinkCollapsed": false,
                "unlinkedCollapsed": true
              }
            }
          },
          {
            "id": "12e60472abe9c859",
            "type": "leaf",
            "state": {
              "type": "outgoing-link",
              "state": {
                "file": "Habits/habit tracker.md",
                "linksCollapsed": false,
                "unlinkedCollapsed": true
              }
            }
          },
          {
            "id": "e2c6bfdead4914a8",
            "type": "leaf",
            "state": {
              "type": "tag",
              "state": {
                "sortOrder": "frequency",
                "useHierarchy": true
              }
            }
          },
          {
            "id": "463380e277dc0327",
            "type": "leaf",
            "state": {
              "type": "outline",
              "state": {
                "file": "Habits/habit tracker.md"
              }
            }
          },
          {
            "id": "4a2e09e4b545c626",
            "type": "leaf",
            "state": {
              "type": "advanced-tables-toolbar",
              "state": {}
            }
          },
          {
            "id": "9a70bafa99f37cf3",
            "type": "leaf",
            "state": {
              "type": "calendar",
              "state": {}
            }
          },
          {
            "id": "4dea8b1c71d0c92e",
            "type": "leaf",
            "state": {
              "type": "podcast_player_view",
              "state": {}
            }
          }
        ],
        "currentTab": 5
      },
      {
        "id": "90b047de25c58d9e",
        "type": "tabs",
        "dimension": 48.920187793427225,
        "children": [
          {
            "id": "11d879d9c6bf5b32",
            "type": "leaf",
            "state": {
              "type": "localgraph",
              "state": {
                "file": "Habits/habit tracker.md",
                "options": {
                  "collapse-filter": true,
                  "search": "",
                  "localJumps": 1,
                  "localBacklinks": true,
                  "localForelinks": true,
                  "localInterlinks": false,
                  "showTags": false,
                  "showAttachments": false,
                  "hideUnresolved": false,
                  "collapse-color-groups": false,
                  "colorGroups": [
                    {
                      "query": "tag:lesson",
                      "color": {
                        "a": 1,
                        "rgb": 5429216
                      }
                    },
                    {
                      "query": "tag:#subject",
                      "color": {
                        "a": 1,
                        "rgb": 5427424
                      }
                    },
                    {
                      "query": "template",
                      "color": {
                        "a": 1,
                        "rgb": 14736466
                      }
                    },
                    {
                      "query": "javascript",
                      "color": {
                        "a": 1,
                        "rgb": 5431378
                      }
                    },
                    {
                      "query": "",
                      "color": {
                        "a": 1,
                        "rgb": 5431473
                      }
                    }
                  ],
                  "collapse-display": false,
                  "showArrow": false,
                  "textFadeMultiplier": 0,
                  "nodeSizeMultiplier": 1,
                  "lineSizeMultiplier": 1,
                  "collapse-forces": true,
                  "centerStrength": 0.518713248970312,
                  "repelStrength": 10,
                  "linkStrength": 1,
                  "linkDistance": 250,
                  "scale": 0.5087618855792605,
                  "close": true
                }
              }
            }
          }
        ]
      },
      {
        "id": "fe83e4da6f72c91e",
        "type": "tabs",
        "dimension": 18.779342723004692,
        "children": [
          {
            "id": "d2e845df7e0b5e7b",
            "type": "leaf",
            "state": {
              "type": "online.tokuhirom.obsidian-pomodoro-plugin",
              "state": {}
            }
          }
        ]
      }
    ],
    "direction": "horizontal",
    "width": 416.5
  },
  "left-ribbon": {
    "hiddenItems": {
      "switcher:Open quick switcher": false,
      "canvas:Create new canvas": false,
      "daily-notes:Open today's daily note": false,
      "graph:Open graph view": false,
      "templates:Insert template": false,
      "command-palette:Open command palette": false,
      "audio-recorder:Start/stop recording": false,
      "obsidian-excalidraw-plugin:Create new drawing": false,
      "table-editor-obsidian:Advanced Tables Toolbar": false,
      "smart-random-note:Open Random Note from Search": false,
      "obsidian-spaced-repetition:Review flashcards": false,
      "darlal-switcher-plus:Open in Headings Mode": false,
      "darlal-switcher-plus:Open Symbols for the active editor": false,
      "workspaces:Manage workspace layouts": false,
      "periodic-notes:Open today": false,
      "dbfolder:Create a new database table": false
    }
  },
  "active": "dcf1d85d92a2e6d3",
  "lastOpenFiles": [
    "journal/31-Jul.md",
    "Habits/habit tracker.md",
    "templates/Daily note template.md",
    "Habits/chart.md",
    "journal/30-Jul.md",
    "journal/28-Jul.md",
    "journal/29-Jul.md",
    "journal/27-Jul.md",
    "Home.md",
    "taki/2023-07-11.md",
    "Habits",
    "journal/2023-07-30.md",
    "journal/2023-07-31.md",
    "taki/2023-07-30.md",
    "javascript/introduction/Introduction and What Is JavaScript.md",
    "journal/07-30.md",
    "2023-07-30.md",
    "journal",
    "taki/2023-07-30 1.md",
    "yinote_Getting started with YiNote - YouTube.md",
    "Attachments/neom-9hWJs7iblh8-unsplash.jpg",
    "Attachments/obsidian-icon.ico",
    "Attachments",
    "taki/2023-07-24.md",
    "taki/2023-07-25.md",
    "Untitled 1",
    "subjects/chimie/Chimie.md",
    "subjects/prog/prog.md",
    "README.md",
    "javascript/introduction",
    "javascript/introduction/Introduction.md",
    "templates/taki.md",
    "javascript",
    "Recording 20230730004134.webm",
    "Excalidraw",
    "Untitled.canvas",
    "dvr",
    "physique/intraction electrique/Untitled.canvas"
  ]
}